<Properties StartupConfiguration="{8002660E-4080-49AA-998B-5F4DE820A13B}|">
  <MonoDevelop.Ide.Workbench ActiveDocument="Controllers/HomeController.cs">
    <Files>
      <File FileName="Controllers/HomeController.cs" Line="1" Column="1" />
    </Files>
  </MonoDevelop.Ide.Workbench>
  <MonoDevelop.Ide.Workspace ActiveConfiguration="Debug" />
  <MonoDevelop.Ide.ItemProperties.ComicBookGallery PreferredExecutionTarget="MonoDevelop.Default" FirstBuild="True" />
  <MonoDevelop.Ide.DebuggingService.Breakpoints>
    <BreakpointStore />
  </MonoDevelop.Ide.DebuggingService.Breakpoints>
  <MonoDevelop.Ide.DebuggingService.PinnedWatches />
  <MultiItemStartupConfigurations />
</Properties>